coshed_ebusd/__init__.py
coshed_ebusd/analysis.py
coshed_ebusd/cli.py
coshed_ebusd/click_glue.py
coshed_ebusd/configuration_files.py
coshed_ebusd/csv_glue.py
coshed_ebusd/defaults.py
coshed_ebusd-0.2.0.dist-info/entry_points.txt
coshed_ebusd-0.2.0.dist-info/COPYING
coshed_ebusd-0.2.0.dist-info/WHEEL
coshed_ebusd-0.2.0.dist-info/METADATA
coshed_ebusd-0.2.0.dist-info/RECORD
