Metadata-Version: 2.1
Name: coshed-ebusd
Version: 0.2.0
Summary: ebusd helper for lazy developer(s)
Author: doubleO8
Author-email: wb008@hdm-stuttgart.de
Requires-Python: >=3.6.2,<4.0.0
Classifier: Programming Language :: Python :: 3
Classifier: Programming Language :: Python :: 3.7
Classifier: Programming Language :: Python :: 3.8
Classifier: Programming Language :: Python :: 3.9
Requires-Dist: coshed-flask (>=0.15.0,<0.16.0)
Requires-Dist: requests (>=2.27.1,<3.0.0)
